ibisgraph/__init__.py
ibisgraph/graph.py
ibisgraph/centrality/__init__.py
ibisgraph/centrality/degrees.py
ibisgraph/centrality/page_rank.py
ibisgraph/clustering/__init__.py
ibisgraph/clustering/label_propagation.py
ibisgraph/pregel/__init__.py
ibisgraph/pregel/models.py
ibisgraph/pregel/pregel.py
ibisgraph/similarity/__init__.py
ibisgraph/similarity/similarity.py
ibisgraph/traversal/__init__.py
ibisgraph/traversal/shortest_paths.py
ibisgraph-0.1.0.dist-info/METADATA
ibisgraph-0.1.0.dist-info/WHEEL
ibisgraph-0.1.0.dist-info/licenses/LICENSE
ibisgraph-0.1.0.dist-info/licenses/NOTICE
ibisgraph-0.1.0.dist-info/RECORD
