Metadata-Version: 2.4
Name: ibisgraph
Version: 0.1.0
Summary: Pregel-based graph algorithms on top of Ibis project
License-File: LICENSE
License-File: NOTICE
Requires-Python: >=3.11
Requires-Dist: ibis-framework
Requires-Dist: loguru>=0.7
